MANIFEST.in
README.rst
setup.py
drosophila_eye_map/__init__.py
drosophila_eye_map/inspect_weightmap.py
drosophila_eye_map/make_buchner_interommatidial_distance_figure.py
drosophila_eye_map/plot_receptors_vtk.py
drosophila_eye_map/precompute_buchner71_optics.py
drosophila_eye_map/precomputed_buchner71.py
drosophila_eye_map/receptor_directions_buchner71.csv
drosophila_eye_map/receptor_weight_matrix_64_buchner71.mat
drosophila_eye_map/trace_buchner_1971.py
drosophila_eye_map/util.py
drosophila_eye_map.egg-info/PKG-INFO
drosophila_eye_map.egg-info/SOURCES.txt
drosophila_eye_map.egg-info/dependency_links.txt
drosophila_eye_map.egg-info/entry_points.txt
drosophila_eye_map.egg-info/top_level.txt