Metadata-Version: 1.0
Name: drosophila-eye-map
Version: 0.5.0
Summary: eye map of Drosophila melanogaster
Home-page: https://github.com/strawlab/drosophila_eye_map
Author: Andrew Straw
Author-email: strawman@astraw.com
License: UNKNOWN
Platform: UNKNOWN
